patchwork/contrib/common/__init__.py
patchwork/contrib/common/connector.py
patchwork/contrib/fastapi/__init__.py
patchwork/contrib/fastapi/dependencies.py
patchwork/contrib/fastapi/entities.py
patchwork/contrib/fastapi/settings.py
patchwork/contrib/fastapi/tokens/__init__.py
patchwork/contrib/fastapi/tokens/jwt.py
patchwork/contrib/fastapi/tokens/middleware.py
patchwork/contrib/fastapi/tokens/utils.py
tests/__init__.py
tests/test_connector.py
tests/test_fastapi_jwt.py
patchwork_contrib-0.2.5.dist-info/LICENSE
patchwork_contrib-0.2.5.dist-info/METADATA
patchwork_contrib-0.2.5.dist-info/WHEEL
patchwork_contrib-0.2.5.dist-info/top_level.txt
patchwork_contrib-0.2.5.dist-info/RECORD
