Metadata-Version: 2.1
Name: patchwork-contrib
Version: 0.2.5
Summary: Patchwork Contrib
Home-page: 
Author: Pawel Pecio
Author-email: 
Classifier: Development Status :: 5 - Production/Stable
Classifier: License :: OSI Approved :: MIT License
Classifier: Operating System :: POSIX :: Linux
Classifier: Programming Language :: Python :: 3.7
Classifier: Programming Language :: Python :: Implementation :: CPython
Classifier: Topic :: Software Development :: Libraries :: Application Frameworks
License-File: LICENSE
Requires-Dist: patchwork-core ~=0.2
Requires-Dist: aiohttp
Provides-Extra: fastapi
Requires-Dist: fastapi >=0.100 ; extra == 'fastapi'
Requires-Dist: python-jose[cryptography] ; extra == 'fastapi'
Provides-Extra: tortoise
Requires-Dist: tortoise-orm ; extra == 'tortoise'
